stripend/__init__.py
stripend/stripend.py
stripend-0.1.2.dist-info/LICENSE
stripend-0.1.2.dist-info/METADATA
stripend-0.1.2.dist-info/WHEEL
stripend-0.1.2.dist-info/top_level.txt
stripend-0.1.2.dist-info/RECORD
