Metadata-Version: 2.1
Name: stripend
Version: 0.1.2
Summary: A Python module that includes utility methods for making your code shorter, more flexible, and smarter.
Home-page: https://github.com/TrueMyst/stripend
Author: TrueMyst
License: MIT
Project-URL: Issue tracker, https://github.com/TrueMyst/stripend/issues
Keywords: utilities,utils,python,code,pyutils
Platform: UNKNOWN
Classifier: Development Status :: 5 - Production/Stable
Classifier: Intended Audience :: Developers
Classifier: Operating System :: OS Independent
Classifier: License :: OSI Approved :: MIT License
Classifier: Natural Language :: English
Classifier: Programming Language :: Python :: 3
Classifier: Topic :: Utilities
Classifier: Topic :: Software Development :: Libraries
License-File: LICENSE
